Workbook

Sheet Systems_250408
B1: Provider | C1: ID / AIM | D1: Type | E1: Server Name/HostName | F1: OS/Image | G1: Server Spec | H1: SSH IP/PORT | I1: ACG | J1: AuthKey | K1: IP(Public) | L1: Storage(Default 50GB) | M1: Service
B2: NCP | C2: webadmin@veritasmedia.co.kr | D2: Classic | E2: zusam-ml-2 | F2: centos-7.8-64 | G2: [GPU] Tesla P40 2GPU, 8vCPU, 60GB Mem, 50GB Disk [g1] | H2: 106.10.40.234/33909 | I2: zusam-ml | J2: zusam-ml-2 | K2: 115.85.181.93 | L2: [SSD] zusam-ml-data 1000 GB /dev/xvdb
D3: Classic | E3: veritasconnect-report | F3: centos-7.8-64 | G3: [Standard] 4vCPU, 16GB Mem, 50GB Disk [g2] | H3: 106.10.40.234/33908 | I3: veritas-report | J3: veritasconnect-report | K3: 118.67.131.218 | L3: [SSD] veritasconnect-report-data 500 GB /dev/xvdb
D4: Classic | E4: vm-resource | F4: centos-7.8-64 | G4: [Standard] 2vCPU, 4GB Mem, 50GB Disk [g1] | H4: 106.10.40.234/10001 | I4: vm-resource | J4: vm-resource | K4: 101.101.208.246 | L4: Default
D5: Classic | E5: dangolmart-web | F5: centos-7.8-64 | G5: [Standard] 2vCPU, 4GB Mem, 50GB Disk [g1] | H5: 106.10.40.234/1024 | I5: ncloud-default-acg | J5: dangolmart2 | K5: 49.50.172.162 | L5: Default
D6: Classic | E6: veritasmedia-main-web | F6: CentOS 7.8 | G6: [Standard] 4vCPU, 16GB Mem, 50GB Disk [g2] | H6: 106.10.40.234/33905 | I6: veritasmedia-main-web | J6: veritasmedia-main-web | K6: 101.101.217.176 | L6: Default
D7: Classic | E7: veritasconnect-infra | F7: centos-7.8-64 | G7: [Standard] 2vCPU, 8GB Mem, 50GB Disk [g2] | H7: 106.10.40.234/33904 | I7: veritasmedia-emr | J7: emr_new | K7: 49.50.163.198 | L7: Default
D8: Classic | E8: veritasmedia-main-db | F8: centos-7.8-64 | G8: [Standard] 4vCPU, 8GB Mem, 50GB Disk [g1] | H8: 106.10.40.234/33902 | I8: ncloud-default-acg | J8: veritasmedia-main-db | K8: 118.67.143.245 | L8: Default
D9: Classic | E9: veritasmedia-db | F9: CentOS 6.6 | G9: [Standard] 4vCPU, 8GB Mem, 50GB Disk [g1] | H9: 220.230.119.30/Default | I9: ncloud-default-acg | J9: nc-veritasmedia | K9: 220.230.114.221 | L9: Default
D10: Classic | E10: veritasmedia | F10: centos-6.6-64 | G10: [Standard] 4vCPU, 8GB Mem, 50GB Disk [g1] | H10: 220.230.119.30/1044 | I10: ncloud-default-acg | J10: nc-veritasmedia | K10: 220.230.119.236 | L10: Default
D12: VPC | E12: zusam-ui | F12: Rocky Linux 8.10 | G12: ci4-g2-s50(vCPU 4EA, Memory 8GB, [SSD]Disk 50GB) | H12: 211.188.61.202/Default | I12: - | J12: zusam-ml-2 | K12: 211.188.61.202 | L12: zusam-ui-storage | SSD | 200 GB | /dev/xvdb
D13: VPC | E13: vap-affilate | F13: Rocky Linux 8.10 | G13: s4-g2-s50(vCPU 4EA, Memory 16GB, [SSD]Disk 50GB) | H13: 175.45.194.87/Default | K13: 175.45.194.87 | L13: vap-affilate-storage | SSD | 150 GB | /dev/xvdb
D14: VPC | E14: ai-platform-server | F14: Rocky Linux 8.10 | G14: m8-g2-s50(vCPU 8EA, Memory 64GB, [SSD]Disk 50GB) | H14: 223.130.128.222/15150 | I14: ai-platform-acg | J14: ai-platform-key | K14: 223.130.128.222 | L14: ai-platform-server-storage | SSD | 2000 GB | /dev/xvdb | N14: 45791
C16: miraeasset@veritasmedia.co.kr | D16: Classic | E16: miraeasset | F16: centos-7.3-64 | G16: [Standard] 2vCPU, 4GB Mem, 50GB Disk [g1] | H16: 101.101.167.16/1024 | I16: ncloud-default-acg | J16: miraeasset | K16: 106.10.33.167 | L16: [HDD] miraeHdd 1000 GB /dev/xvdb | M16: partnersclub.co.kr
C18: vc_media@naver.com | E18: 네이버웍스 계정_법인
C20: mdev | D20: Classic | E20: unmeglobal | F20: LAMP-centos-7.3.64 | G20: [Standard] 2vCPU, 4GB Mem, 50GB Disk [g1] | H20: 210.89.190.94/1030 | I20: ncloud-default-acg | J20: daemyungevent | K20: 49.50.172.195 | M20: kbeinc.co.kr | N20: (종료) 25.06.23
D21: VPC | E21: koreainvestment-event-com-1 | F21: ubuntu-22.04-base | G21: ci2-g3(vCPU 2EA, Memory 4GB) | J21: koreainvestment | K21: 223.130.154.29 | M21: koreainvestment-event.com koreainvestment-pension.com
D22: VPC | E22: koreainvestment-dev | F22: ubuntu-22.04-base | G22: m2-g3(vCPU 2EA, Memory 16GB) | J22: koreainvestment | K22: 211.188.52.193
D23: VPC | E23: koreainvestment-api | F23: ubuntu-22.04-base | G23: s2-g3(vCPU 2EA, Memory 8GB) | J23: koreainvestment | K23: 211.188.54.248
D24: VPC | E24: koreainvestment-pension-1 | F24: ubuntu-22.04-base | G24: s2-g3(vCPU 2EA, Memory 8GB) | J24: koreainvestment | K24: 211.188.58.158
D25: VPC | E25: koreainvestment-event-2 | F25: ubuntu-22.04-base | G25: s2-g3(vCPU 2EA, Memory 8GB) | J25: koreainvestment-event | K25: 223.130.161.133
D26: VPC | E26: koreainvestment-event-1 | F26: ubuntu-22.04-base | G26: s2-g3(vCPU 2EA, Memory 8GB) | J26: koreainvestment-event | K26: 175.45.201.65
D27: LB | E27: koreainvestment-pension-com | H27: koreainvestment-pension-com-102514437-96d7d508116c.kr.lb.naverncp.com | K27: 223.130.131.82
D54: LB | E54: koreainvestment-event-com | H54: koreainvestment-event-com-102151686-472e31d28ac3.kr.lb.naverncp.com | K54: 211.188.50.214
B77: AWS | C77: license@veritasmedia.co.kr
C78: qpflxktmaleu123!@#
B96: Local | C96: root | D96: Desktop | E96: aip | F96: Rocky Linux 9.5 | H96: 192.168.1.110 / Default | K96: 192.168.1.110 | M96: 이상훈
C97: root | D97: Desktop | E97: zusam | F97: CentOS Linux release 8.5.2111 | H97: 192.168.1.116 / Default | K97: 192.168.1.116 | M97: 이상훈
C98: AI_DEV / veritas! | D98: MacMIni | E98: vc_pfmc | F98: macOS 15.4 24E248 arm64 | G98: Apple M2 / 250GB / 16GB | H98: 192.168.1.30 / Default | I98: - | J98: - | K98: 192.168.1.30 | M98: 이상훈
C99: 기재 확인 | D99: MacMIni | E99: 기재 확인 | F99: 기재 확인 | G99: 기재 확인 | H99: 192.168.1.5 / Default | K99: 192.168.1.5 | L99: /data_ext(//192.168.1.123/Dev) | M99: 김창혁
M100: 김동준
C101: veritasmedia_lab / veritas@k2 | D101: Desktop | F101: Windows11 | G101: RemoteAccess Gateway | H101: 192.168.1.123 | K101: 192.168.1.123 | M101: 공통
C102: root, aip-dev | D102: Desktop | E102: aip-dev | F102: Rocky Linux 8.10 | G102: i9-12900K 3.20 GHz / NVIDIA GeForce GTX 1660 /128GB | H102: 192.168.1.77/14142 | K102: 192.168.1.77 | M102: 공통
C103: vm_user / veritas@k2 | D103: Desktop | F103: Windows11 | H103: 192.168.1.211 | K103: 192.168.1.211 | L103: (외부 반출) 25.04.28 > 이진우 | M103: 이진우

Sheet Hantu
B5: Ebiz자동화 | C5: Admin | D5: http://223.130.154.29:3000/admin/event/ebiz/financial
B6: Ebiz | C6: Staging | D6: http://223.130.154.29:3000/ebiz/pc
C7: Live | D7: https://koreainvestment-event.com/ebiz/pc/
B8: 마케팅 | C8: Staging | D8: http://223.130.154.29:3000/pb/pc
C9: Live | D9: https://koreainvestment-event.com/pb/pc/
B10: 연금부 | C10: Live | D10: https://koreainvestment-pension.com/pc/tab_02/index.html
B11: 홍보실 | C11: Live | D11: https://hantu.zusam.ai:8509

Sheet MiraeAsset
B7: Platform | C7: URL | D7: DeveloperID | E7: Updated
B8: google | C8: https://play.google.com/console | D8: veritasmedia.dev@gmail.com | E8: 45756
B9: apple

Sheet Kakao_AWS_Cost_Instancess
A1: 서비스 | B1: EC2-인스턴스($) | C1: Elastic Load Balancing($) | D1: VPC($) | E1: Tax($) | F1: EC2-기타($) | G1: Elastic File System($) | H1: Route 53($) | I1: S3($) | J1: Cost Explorer($) | K1: 총 비용($) | L1: 원화(당일 환율 1485.53원 기준) | M1: 월 평균(최근 1년)
A2: 서비스 합계 | B2: 3107.375 | C2: 911.58636 | D2: 471.17061 | E2: 470.87 | F2: 189.46212 | G2: 13.468727 | H2: 12.045687 | I2: 2.1211339 | J2: 1.2922449 | K2: 5179.3918 | L2: =SUBTOTAL(9,L3:L14) -> 7694200.1
A3: 45383 | B3: 227.9808 | C3: 68.864594 | D3: 36.530508 | E3: 34.98 | F3: 14.13609 | G3: 1.0318237 | H3: 1.0020104 | I3: 0.17677779 | J3: 0.10786373 | K3: 384.81047 | L3: 571601.88 | M3: =AVERAGE(L3:L14) -> 641183.34
A4: 45413 | B4: 235.6992 | C4: 71.233445 | D4: 37.230411 | E4: 36.06 | F4: 14.136095 | G4: 1.0450631 | H4: 1.0023148 | I4: 0.17682011 | J4: 0.10586854 | K4: 396.68922 | L4: 589298.91
A5: 45444 | B5: 228.096 | C5: 68.857478 | D5: 36.032649 | E5: 34.94 | F5: 14.136099 | G5: 1.0556889 | H5: 1.001974 | I5: 0.17674087 | J5: 0.10252214 | K5: 384.39915 | L5: 571004.39
A6: 45474 | B6: 235.6992 | C6: 71.195446 | D6: 37.230493 | E6: 36.05 | F6: 14.136097 | G6: 1.0829985 | H6: 1.0021648 | I6: 0.17678353 | J6: 0.10239774 | K6: 396.67558 | L6: 589267.68
A7: 45505 | B7: 235.584 | C7: 71.208017 | D7: 37.2457 | E7: 36.06 | F7: 14.136096 | G7: 1.1073002 | H7: 1.0024844 | I7: 0.17678528 | J7: 0.099815882 | K7: 396.6202 | L7: 589187.31
A8: 45536 | B8: 228.096 | C8: 68.849277 | D8: 36.033851 | E8: 34.94 | F8: 14.136093 | G8: 1.1282704 | H8: 1.0021816 | I8: 0.17666989 | J8: 0.099512731 | K8: 384.46186 | L8: 571097.66
A9: 45566 | B9: 235.5264 | C9: 71.180667 | D9: 37.248824 | E9: 36.06 | F9: 14.136095 | G9: 1.1363758 | H9: 1.0020312 | I9: 0.17678877 | J9: 0.095677688 | K9: 396.56286 | L9: 589102.68
A10: 45597 | B10: 260.23501 | C10: 74.321848 | D10: 38.769492 | E10: 39.16 | F10: 15.725267 | G10: 1.1468473 | H10: 1.0021884 | I10: 0.17675507 | J10: 0.10638173 | K10: 430.64379 | L10: 639777.75
A11: 45627 | B11: 312.85601 | C11: 88.676949 | D11: 44.642151 | E11: 46.74 | F11: 18.696046 | G11: 1.1587142 | H11: 1.002026 | I11: 0.17675688 | J11: 0.12033677 | K11: 514.069 | L11: 763695.3
A12: 45658 | B12: 312.7632 | C12: 88.140519 | D12: 44.672821 | E12: 46.68 | F12: 18.696048 | G12: 1.1742056 | H12: 1.0021404 | I12: 0.17678146 | J12: 0.11663013 | K12: 513.42234 | L12: 762735.98
A13: 45689 | B13: 282.5696 | C13: 80.426852 | D13: 40.379725 | E13: 42.46 | F13: 18.696044 | G13: 1.1899144 | H13: 1.0217392 | I13: 0.17672032 | J13: 0.11645835 | K13: 467.03705 | L13: 693834.69
A14: 45717 | B14: 312.26954 | C14: 88.631272 | D14: 45.153982 | E14: 46.74 | F14: 18.696045 | G14: 1.2115251 | H14: 1.0024316 | I14: 0.17675391 | J14: 0.11877948 | K14: 514.00033 | L14: 763595.85

Sheet AWS_Kakao_costs_ELB
A1: [KAKAOPAY_SEC] COST_ELB Only
C3: 2025.04.10
B4: 총 비용($) | C4: KRW | D4: =1485.53 -> 1485.53
A5: 합계 | B5: 936.46194 | C5: =$D$4*B5 -> 1391142.3
A6: 45383 | B6: 68.864594 | C6: =$D$4*B6 -> 102300.42
A7: 45413 | B7: 71.233445 | C7: =$D$4*B7 -> 105819.42
A8: 45444 | B8: 68.857478 | C8: =$D$4*B8 -> 102289.85
A9: 45474 | B9: 71.195446 | C9: =$D$4*B9 -> 105762.97
A10: 45505 | B10: 71.208017 | C10: =$D$4*B10 -> 105781.64
A11: 45536 | B11: 68.849277 | C11: =$D$4*B11 -> 102277.67
A12: 45566 | B12: 71.180667 | C12: =$D$4*B12 -> 105741.02
A13: 45597 | B13: 74.321848 | C13: =$D$4*B13 -> 110407.33
A14: 45627 | B14: 88.676949 | C14: =$D$4*B14 -> 131732.27
A15: 45658 | B15: 88.140519 | C15: =$D$4*B15 -> 130935.38
A16: 45689 | B16: 80.426852 | C16: =$D$4*B16 -> 119476.5
A17: 45717 | B17: 88.631272 | C17: =$D$4*B17 -> 131664.41
A18: 45748 | B18: 24.875574 | C18: =$D$4*B18 -> 36953.411
B19: =SUM(B6:B18) -> 936.46194 | C19: =SUM(C6:C18) -> 1391142.3

Sheet old_KakakoPaySec_수익성 검토
A2: [카카오페이증권] 적정 용역금액 검토
A6: 고객사 | B6: 계약금액(월) | C6: 비용1(AWS) | D6: 수익(월) | E6: 매출(연간) | F6: 투입인력 | G6: 노임 단가 | H6: 투입율(M/M) | I6: 투입인건비(월) | J6: 추산 손익(년간) | K6: [참고] 용역계약 범위
A7: 카카오페이증권 | B7: 1500000 | C7: =AVERAGE(Kakao_AWS_Cost_Instancess!L12:L14) -> 740055.51 | D7: =B7-C7 -> 759944.49 | E7: =(B7-C7)*12 -> 9119333.9 | F7: 프로젝트 총괄 | G7: ='개발자 노임단가'!C13 -> 9145473 | H7: 0.1 | I7: =G7*H7 -> 914547.3 | J7: =(D7-I12)*12 -> -50847234 | K7: 홈페이지 운영 (퍼블, 개발, 운영)
F8: 개발 - 퍼블 / 초급 | G8: ='개발자 노임단가'!C15 -> 6727260 | H8: 0.2 | I8: =G8*H8 -> 1345452 | K8: 카카오페이증권 ADMIN 개발 / 운영
F9: 개발 - FE / 중급 | G9: ='개발자 노임단가'!C17 -> 6943457 | H9: 0 | I9: =G9*H9 -> 0 | K9: 시스템 운영
F10: 개발 - BE / 고급 | G10: ='개발자 노임단가'!C18 -> 6099042 | H10: 0.2 | I10: =G10*H10 -> 1219808.4 | K10: 네트워크, 보안
F11: 시스템 운용(AWS Manager) | G11: ='개발자 노임단가'!C20 -> 5058021 | H11: 0.3 | I11: =G11*H11 -> 1517406.3
E12: =E7 -> 9119333.9 | I12: =SUM(I7:I11) -> 4997214 | O12: =150*12+500 -> 2300
O13: =O12/12 -> 191.66667
C15: t2.small | D15: 1
C16: t2.large | D16: 2
C17: t2.medium | D17: 1 | I17: 적정 용역비 산출(월) | J17: =(투입인건비 + 호스팅 비용 + 기술료)
C18: t3.large | D18: 1 | J18: =ROUNDDOWN((I12 + C12 ), -3) -> 4997000 | K18: 원단위 절사
K19: =J18*12 -> 59964000
J20: * 기술료 = 투입인건비 * 20%
H22: =22*0.3 -> 6.6
B25: [참고] Hosting 이용 내역 상세

Sheet Fin_KakakoPaySec_수익성 검토 (2)
A2: [카카오페이증권] 적정 용역금액 검토
A6: 계약금액(월) | B6: 비용(AWS) | C6: 수익(월) | D6: 투입인력 | E6: 노임 단가 | F6: 투입율(M/M) | G6: 투입인건비 | H6: 추산 손익(년간) | J6: [참고] 용역계약 범위
A7: 1500000 | B7: =AVERAGE(Kakao_AWS_Cost_Instancess!L12:L14) -> 740055.51 | C7: =A7-B7 -> 759944.49 | D7: 프로젝트 총괄 | E7: ='개발자 노임단가'!C13 -> 9145473 | F7: 0.1 | G7: =E7*F7 -> 914547.3 | H7: =C7*12 - G12 -> 4122119.9 | J7: 홈페이지 운영 (퍼블, 개발, 운영)
D8: 개발 - 퍼블 / 초급 | E8: ='개발자 노임단가'!C15 -> 6727260 | F8: 0.2 | G8: =E8*F8 -> 1345452 | J8: 카카오페이증권 ADMIN 개발 / 운영
D9: 개발 - FE / 중급 | E9: ='개발자 노임단가'!C17 -> 6943457 | F9: 0 | G9: =E9*F9 -> 0 | J9: 시스템 운영
D10: 개발 - BE / 고급 | E10: ='개발자 노임단가'!C18 -> 6099042 | F10: 0.2 | G10: =E10*F10 -> 1219808.4 | J10: 네트워크, 보안
D11: 시스템 운용(AWS Manager) | E11: ='개발자 노임단가'!C20 -> 5058021 | F11: 0.3 | G11: =E11*F11 -> 1517406.3
A12: =A7*12 -> 18000000 | B12: =B7*12 -> 8880666.1 | G12: =SUM(G7:G11) -> 4997214 | H12: = 총 용역비 - 호스팅비 - 투입인건비
B15: t2.small | C15: 1
B16: t2.large | C16: 2
B17: t2.medium | C17: 1
B18: t3.large | C18: 1
I20: * 기술료 = 투입인건비 * 20%
A25: [참고] Hosting 이용 내역 상세

Sheet 개발자 노임단가
B2: 2025년 적용 SW기술자 평균임금 공표
B4: 통계법 제27조(통계의 공표)에 따라 『2024년 SW기술자 임금실태조사 (통계승인 제375001호)』의 결과로 다음과 같이 SW기술자 평균임금을 공표합니다.
B6: 【SW기술자 평균임금】
F7: (단위: 원)
B8: 구 분 | C8: 월평균임금(M/M) | D8: 일평균임금 (M/D) | E8: 시간평균임금(M/H) | F8: 포함직무
B9: ① IT기획자 | C9: 11597656 | D9: 562993 | E9: 70374
B10: ② IT컨설턴트 | C10: 9706020 | D10: 471166 | E10: 58896 | F10: 정보보호컨설턴트
B11: ③ 업무분석가 | C11: 8997359 | D11: 436765 | E11: 54596
B12: ④ 데이터분석가 | C12: 7751183 | D12: 376271 | E12: 47034
B13: ⑤ IT PM | C13: 9145473 | D13: 443955 | E13: 55494
B14: ⑥ IT아키텍트 | C14: 10147745 | D14: 492609 | E14: 61576 | F14: SW아키텍트, 데이터아키텍트, Infrastructure아키텍트, 데이터베이스아키텍트
B15: ⑦ UI/UX기획/개발자 | C15: 6727260 | D15: 326566 | E15: 40821 | F15: UI/UX기획자, UI/UX개발자
B16: ⑧ UI/UX디자이너 | C16: 5176203 | D16: 251272 | E16: 31409
B17: ⑨ 응용SW개발자 | C17: 6943457 | D17: 337061 | E17: 42133 | F17: 빅데이터개발자, 인공지능개발자
B18: ⑩ 시스템SW개발자 | C18: 6099042 | D18: 296070 | E18: 37009 | F18: 임베디드SW개발자
B19: ⑪ 정보시스템운용자 | C19: 10154626 | D19: 492943 | E19: 61618 | F19: 데이터베이스운용자, NW엔지니어, IT시스템운용자
B20: ⑫ IT지원기술자 | C20: 5058021 | D20: 245535 | E20: 30692
B21: ⑬ IT마케터 | C21: 11056617 | D21: 536729 | E21: 67091 | F21: SW제품기획자, IT서비스기획자, IT기술영업
B22: ⑭ IT품질관리자 | C22: 9692094 | D22: 470490 | E22: 58811
B23: ⑮ IT테스터 | C23: 3570557 | D23: 173328 | E23: 21666
B24: ⑯ IT감리 | C24: 10351376 | D24: 502494 | E24: 62812
B25: ⑰ 정보보안전문가 | C25: 9857100 | D25: 478500 | E25: 59813 | F25: 정보보호관리자, 침해사고대응전문가
B27: <본 평균임금을 SW사업대가 활용시 유의사항> ※ 본 조사결과는 SW사업에서 SW기술자 인건비 평균 값임을 고려하여 활용 가능하며, 수·발주자간 자율적 협의에 의해서도 유연하게 적용할 수 있음 * SW기술자 평균임금은 소프트웨어진흥법 제46조(적정 대가 지급 등) 4항 ‘소프트웨어기술자의 인건비 기준’을 지칭함 * SW기술자 평균임금은 기본급, 제수당, 상여금, 퇴직급여충당금, 법인부담금(4대보험)을 모두 포함한 결과임 * 일평균임금은 월평균임금÷`24년 평균근무일수(20.6일), 시간평균임금은 일평균임금÷8시간 으로 각각 산정함 * 월평균 근무일수는 휴일, 법정공휴일 등을 제외한 업체가 응답한 근무일의 평균이며, 이는 개인의 휴가 사용 여부와는 무관함 * SW기술자 평균임금은 전년 대비 4.2% 증가함 * 25/75 백분위수는 조사된 직무별 임금의 구간, 분포에 대한 참고 값임(백분위수 : 백분위수는 크기가 있는 값들로 이뤄진 자료를 순서대로 나열했을 때 백분율로 나타낸 특정 위치의 값을 이르는 용어이다. 일반적으로 크기가 작은 것부터 나열하여 가장 작은 것을 0, 가장 큰 것을 100으로 한다.)
B29: [시행일] 2025년 1월 1일부터 2025년 12월 31일까지 적용
A31: 2024년 12월 3일
A32: 한국소프트웨어산업협회장

Sheet 유지보수_전체
B5: 고객사 | D5: 고객사 담당 부서 | E5: 작업 수행 내역(퍼블/개발/시스템 운영/기타) | F5: 작업 담당 | G5: 요청부서/매출인식 | I5: 호스팅 비용(월) | J5: 단순 손익 | K5: 적정개발비(추산,월) | L5: 계약 만료(예정)일 | M5: 참고 사항
G6: 부서 | H6: 유지보수액(월)
B7: 1 | C7: 한국투자증권 | D7: Ebiz | E7: 퍼블/시스템 운영 | F7: 이진영 / 김동준 | G7: 4본부 | H7: =SUM(H26:H28) -> 2420000 | I7: =AVERAGE(G22:G24) -> 1077010 | J7: =SUM(H7:H10)-I7 -> 1817990 | K7: ='old_KakakoPaySec_수익성 검토'!I12*1.1 -> 5496935.4
D8: 마케팅부 | E8: 이벤트 페이지 퍼블 | F8: 이진영 | G8: " | H8: =700000/4 -> 175000 | M8: 분기 70만원
D9: 연금부 | E9: 이벤트 페이지 퍼블 | F9: 이진영 | G9: " | H9: 300000 | M9: 호스팅비용 별도 청구
D10: 홍보실 | E10: 언론홍보 자동화 | F10: 이상훈 | G10: " | H10: 0 | I10: 0 | K10: 0 | M10: AIP 서버 공동 활용
B11: 2 | C11: IBK투자증권 | E11: 홈페이지 / 아이원 뱅크 / HTS / 모바일웹 | F11: 이진영 | G11: 디자인국 | H11: 5000000 | I11: 0 | J11: 0 | K11: 10000000 | M11: 프로젝트 전용 게시판 별도 운영, 내부 프로세스 재조율 필요 | N11: http://lab.veritasmedia.co.kr/redmine/projects/ibk-ui-ux/
B12: 3 | C12: 다올투자증권 | E12: 홈페이지, HTS / 모바일 웹 | F12: 이진영 | G12: 디자인국 | H12: 3000000 | I12: 0 | J12: 0 | K12: =3500000*0.5 -> 1750000 | M12: 서버 운영 없음, File로 전달
B13: 4 | C13: 카카오페이증권 | E13: 홈페이지 / ADMIN / 시스템 운영 / 보안 | F13: 김동준 / 김창혁 | G13: AI플랫폼 | H13: 1500000 | I13: 740000 | J13: =H13-I13 -> 760000 | K13: ='old_KakakoPaySec_수익성 검토'!I12 -> 4997214 | L13: ~ 25.03.31 | M13: 계약 연장 협의(업무범위, 계약 금액 현실화)
B14: 5 | C14: 미래에셋증권 | E14: 파트너스클럽 웹 / 앱(iOS, Android) 개발,운영/ 시스템 운영 | F14: 김동준 / 김창혁 | G14: AI플랫폼 | H14: 1000000 | I14: =(85120+24000+4000)*1.25 -> 141400 | J14: =H14-I14 -> 858600 | K14: ='개발자 노임단가'!C18*0.5 -> 3049521 | L14: ~ 25.09.30 | M14: Android app 등록 중단됨/4.30일 이내 재등록
B15: 6 | C15: 케이프투자증권 | E15: 이벤트 페이지 퍼블 / 시스템 운영 | F15: 이진영 / 김동준 | G15: 1본부 | H15: 0 | I15: =(173120+24000+4000+17470)*1.25 -> 273237.5 | J15: =H15-I15 -> -273237.5
B16: 7 | C16: HomeCC Admin | D16: (케이씨씨글라스) | E16: 이벤트 페이지 퍼블 / ADMIN | F16: 이진영 | G16: 1본부 | H16: 0 | I16: =75000+24000+4000+17470 -> 120470 | J16: =H16-I16 -> -120470 | K16: ='개발자 노임단가'!D15*5 -> 1632830
B17: Total | H17: =SUM(H7:H16) -> 13395000 | I17: =SUM(I7:I16) -> 2352117.5 | J17: =SUM(J7:J16) -> 3042882.5 | K17: =SUM(K7:K16) -> 26926500
G18: 년간 | H18: =H17*12 -> 160740000 | J18: =J17*12 -> 36514590
F21: 2025 | G21: (한투)호스팅비용
F22: 1월 | G22: 1189430
F23: 2월 | G23: 1029380
F24: 3월 | G24: 1012220
F26: 한투_매출(3월) | G26: 개발 | H26: 990000 | I26: PC/Mobile 페이지 퍼블리싱(3ea)
G27: 개발 | H27: 1100000 | I27: 클라우드 웹호스팅(웹서버 1ea)
G28: 개발 | H28: 330000 | I28: PC/Mobile 통합이벤트페이지 수정
G29: 1) | H29: =SUM(H26:H28) -> 2420000
G30: 제작(디자인) | H30: 264000 | I30: 4월 브랜드검색 소재 제작 (총 2개 안)
G31: 제작(디자인) | H31: 1320000 | I31: 해외주식 캠페인 소재 시안 제작 (4ea)
G32: 제작(디자인) | H32: 2508000 | I32: 해외주식 캠페인 소재 베리에이션 (76ea)
G33: 2) | H33: =SUM(H30:H32) -> 4092000
G34: Total | H34: =H33+H29 -> 6512000

Sheet 운영관리_전체_250408
A2: =SUBTOTAL(9,A4:A43) -> 31 | B2: 구분 | D2: Service_name | E2: URL | F2: Server
F3: Cloud | G3: HostName/InstanceID | H3: IP | I3: PORT | J3: ID | K3: PWD | L3: CERT(SSL) | M3: Web_Server/Framework | N3: DB | O3: Services(Start Script) | P3: Source_Path | Q3: Envs | R3: docker Container
A4: =COUNTA(E4:E15) -> 9 | B4: 인프라(공통) | C4: Web app | D4: 매출관리시스템_v1(PHP) | E4: https://sales.veritasmedia.co.kr | F4: NCP | G4: veritasconnect-infra | H4: 49.50.163.198 | I4: 80
C5: Web app | D5: 매출관리시스템_v2(Streamlit) | E5: https://sales.veritasconnect.com:8503 | F5: NCP | G5: veritasmedia-main-web | H5: 101.101.217.176 | I5: 8503
C6: Web app | D6: 경비관리시스템_v1(Streamlit) | E6: https://sales.veritasconnect.com:8507 | F6: NCP | G6: veritasmedia-main-web | H6: 101.101.217.176 | I6: 8507
C7: Web app | D7: 홈페이지 | E7: https://veritasconnect.com | F7: NCP | G7: veritasconnect-infra | H7: 49.50.163.198 | I7: 80 | J7: webadmin | K7: qpflxktm(*)!#%
C9: Web app | D9: Report Center(DA/SA Report) | E9: https://report.veritasconnect.com | F9: NCP | G9: veritasconnect-report | H9: 118.67.131.218 | I9: 80 | J9: zusam | K9: qpflxktm(*)!#%
C10: Web app | D10: VAP(V. Affiliate Platform) | E10: https://vap.veritasconnect.com | G10: veritasconnect-report | H10: 118.67.131.218 | I10: 80
C11: Web app | D11: Coway Report Center
C12: Web app | D12: UTM Validator | E12: https://report.veritasconnect.com/utm/ | F12: NCP | G12: veritasconnect-report | H12: 118.67.131.218 | I12: 80
C13: Web app | D13: Report | E13: http://192.168.1.5/analysis/daily/veritas2024 | F13: MacMini_Local
C14: Web app | D14: WEB UI LIBRARY | E14: http://web.zusam.ai | G14: veritasconnect-infra | H14: 49.50.163.198 | I14: 80
A16: =COUNTA(E16:E22) -> 5 | B16: 운영 | C16: Web app | D16: 한투_퍼블 자동화(Ebiz/Marketing) | E16: https://koreainvestment-event.com/ebiz/pc/ | F16: NCP
D17: [FRONT] | E17: http://223.130.154.29:3000/ebiz/pc | F17: NCP
D18: [ADMIN] | E18: http://223.130.154.29:3000/auth/login | F18: NCP | J18: test | K18: test
D19: 연금부 | E19: https://koreainvestment-pension.com/pc/tab_02/index.html | F19: NCP
C21: Web app | D21: 한투_언론홍보자동화(홍보부) | E21: https://hantu.zusam.ai:8509 | F21: NCP | G21: zusam-ml-2 | H21: 115.85.181.93 | I21: 8509
A23: =COUNTA(E23:E29) -> 5 | B23: 유지보수 | C23: native Web view/Web app | D23: 미래에셋증권 | E23: https://partnersclub.co.kr | F23: NCP
C24: Web app | D24: 카카오페이증권 | E24: https://www.kakaopaysec.com/ | F24: AWS
C25: Web app | D25: 케이프투자증권 | E25: https://www.event-capefn.com/ | F25: NCP
C26: Web app | D26: IBK투자증권 | E26: http://lab.veritasmedia.co.kr/redmine/projects/ibk-ui-ux/ | F26: NCP
D27: 다올투자증권 | E27: https://www.daolsecurities.com/top.jsp | F27: NCP
D28: KCC글라스
A30: =COUNTA(E30:E43) -> 12 | B30: 신규 서비스 | C30: Web app | D30: [AI_메인] | E30: https://zusam.ai | F30: NCP | G30: zusam-ml-2 | H30: 115.85.181.93 | I30: 8502 | L30: certbot | M30: nginx/streamlit | O30: /usr/lib/systemd/system/zusam.service | P30: /data/app/zusam_v2 | Q30: /data/app/zusam_v2/env_zusam
C31: Web app | D31: [AI_챗기반] | E31: https://chat.zusam.ai | F31: NCP | G31: zusam-ml-2 | H31: 115.85.181.93 | L31: certbot | R31: chat.zusam.ai
C32: Web app | D32: [AI_SNS분석] | E32: https://sns.zusam.ai | F32: NCP | G32: zusam-ml-2 | H32: 115.85.181.93 | I32: 8503 | L32: certbot
C33: Web app | D33: [AI_SEO분석] | E33: https://seo.zusam.ai | F33: NCP | G33: zusam-ml-2 | H33: 115.85.181.93 | I33: 8504 | L33: certbot | P33: /data/app/seo_report/ | Q33: /data/app/seo_report/env_seo/
C34: Web app | D34: [AI_KEYWORD분석] | E34: https://keyword.zusam.ai | F34: NCP | G34: zusam-ml-2 | H34: 115.85.181.93 | I34: 8505 | L34: certbot
C35: Web app | D35: [AI_객체인식] | E35: https://yolo.zusam.ai | F35: NCP | G35: zusam-ml-2 | H35: 115.85.181.93 | I35: 8506 | L35: certbot
C36: Web app | D36: [AI_UI 생성] | E36: https://ui.zusam.ai | F36: NCP | G36: zusam-ml-2 | H36: 115.85.181.93 | I36: 7878 | L36: certbot
C37: Web app | D37: [AI_통합메타검색엔진] | E37: https://search.zusam.ai | F37: NCP | G37: zusam-ml-2 | H37: 115.85.181.93 | I37: 4000 | L37: certbot
C39: Web app | D39: [AI 매체화 플랫폼_퍼블 중] | E39: https://zusam.im | F39: NCP | H39: 211.188.61.202
E40: https://tools.zusam.ai | F40: NCP | H40: 211.188.61.202
C41: Web app | D41: [AI_API] | E41: https://api.zusam.ai/api/docs | F41: NCP | H41: 115.85.181.93
D42: [AI_API] OLLAMA | E42: http://zusam.ai:11434 | F42: NCP | H42: 115.85.181.93 | I42: 11434

Sheet Dev_Local
B2: System Spec
B4: IP Address. | C4: OS | D4: CPU | E4: Storage | F4: GPU | G4: GPU_CUDA CORE | H4: GPU_VRAM | I4: Memory | J4: Docker / VM | K4: CMD
B5: 192.168.1.77 | C5: W10 Home | D5: i9-12900K 3.20 GHz | E5: 1TB+1TB++1TB + 500GB+ 4TB(1`*4) > 7.5 TB | F5: NVIDIA GeForce GTX 1660 | G5: 1408 | H5: 6GB | I5: 128GB | J5: vmware | K5: CMD+R > msinfo32 Ctrl + Shift + Esc > 성능 > CPU, 메모리, 디스크, 네트워크, GPU 사용률과 모델명 Windows 키 + R > dxdiag PowerShell > systeminfo > wmic cpu get Name, NumberOfCores, NumberOfLogicalProcessors : CPU 이름, 코어 수, 논리 프로세서 수 > wmic memorychip get Capacity, Speed : 메모리 용량과 속도 > wmic diskdrive get Model, Size : 디스크 모델명과 크기 > wmic path win32_VideoController get Name : GPU | L5: 1000 nvidia-smi 1001 lspci | grep vga 1002 lspci | grep -i vga 1003 free -h 1004 df -h 1005 mount -a 1006 df -h 1007 pvdisplay; 1008 pvdisplay 1009 lsblk 1010 uname -a 1011 lscpu 1012 docker ps -a
B6: 192.168.1.123 | C6: W10 Home | D6: i7-6700 CPU @ 3.40GHz | E6: 256 + 500 + 2TB | F6: NVIDIA GeForce GTX 750 | G6: 512 | H6: 1GB | I6: 32GB(8G*4)
B7: 192.168.1.116 | C7: CentOS 7.3 | D7: i7-7700 CPU @ 3.60GHz | E7: 256 + 500G | F7: GP107 [GeForce GTX 1050 Ti] | G7: 768 | H7: 4GB | I7: 16G | J7: mysql:8.0 / 5.7 | K7: uname -a : 커널 버전, OS 정보 cat /etc/os-release : 배포판 정보 lscpu free -h df -h / lsblk lspci | grep -i vga : GPU 정보 nvidia-smi
B8: 192.168.1.110 | C8: Rocky Linux 9.5 | D8: i7-8700 CPU @ 3.20GHz | E8: 256 + 1TB | F8: GP106 [GeForce GTX 1060 3GB] | G8: 1152 | H8: 3GB | I8: 16G | J8: Redmine + mysql:8.0
D11: GPU | E11: 딥러닝 학습 가능성 | F11: 추론 성능 | G11: 실전 사용 추천
D12: GTX 1660 | E12: 중간급 모델까지 가능 | F12: 충분 | G12: ✅ 추천
D13: GTX 1060 3GB | E13: 제한적 | F13: 가능 | G13: ⚠️ 제한적 추천
D14: GTX 1050 Ti | E14: 매우 제한적 | F14: 가능 | G14: ❌ 비추천
D15: GTX 750 | E15: 거의 불가능 | F15: 낮음 | G15: ❌❌ 사용 비추천

Sheet Payment(25.06)
A5: AIP(AI플랫폼본부) 결제 내역
A6: 결제내역 | B6: Provider | C6: Service/Product | D6: Client | E6: Payment | F6: LastUpdated | G6: URL | H6: AccountInfo | I6: 평균요금/월 | J6: 비고
A7: 2 | B7: AMAZON | C7: AWS | D7: 카카오페이증권 | E7: 4518-****-****-4306 | F7: 2025-06-20 | G7: https://us-east-1.console.aws.amazon.com/billing/home#/paymentpreferences/paymentmethods license@veritasmedia.co.kr | I7: 600000 | J7: 25.6월 기준
A9: 3 | B9: ELEVENLABS.IO | D9: 개발용 | E9: 4518-****-****-4306 | G9: https://elevenlabs.io/app/subscription | H9: zankke@gmail.com | I9: 22 | J9: 매월 청구(구독 취소. 25.06.20)
A10: 5 | B10: OPENAI | C10: CHATGPT | D10: 개발용 | G10: https://platform.openai.com/ | H10: ai@veritasconnect.com | I10: 70000 | J10: "
B11: " | C11: SORA | D11: 개발용 | G11: https://sora.chatgpt.com/ | I11: 0 | J11: 미가입
A12: 6 | B12: " | C12: ChatGPT.com PLUS | D12: 개발용 | G12: https://chatgpt.com/#pricing | H12: ai@veritasconnect.com | I12: 20 | J12: 매월 청구
B13: REPLICATE | C13: Video API | D13: Video생성 | E13: 4518-****-****-4306 | G13: https://replicate.com/account/billing | H13: ai@veritasconnect.com | J13: "
B15: STABILITY AI | C15: Stable Didffusion | D15: 개발용 | E15: 4265-****-****-3648 | H15: ai@veritasconnect.com | J15: 연간 멤버쉽
B16: SERP API | C16: Serp API | D16: 개발용 | E16: 4265-****-****-3648 | G16: https://serpapi.com/ | I16: 50
B17: MidJourney Inc | C17: Midjourney | D17: 개발용 | E17: 4265-****-****-3648 | G17: https://billing.stripe.com/p/login/aEUdRA5Wc8t25a03cc?referer=invoice_receipt | H17: ai@veritasconnect.com | I17: ?
B18: ClipDrop | C18: RemoveBG | D18: 개발용 | E18: 4265-****-****-3648 | H18: ai@veritasconnect.com | I18: 선충전 5000 크레딧 | J18: (25.06.20) 잔여 크레딧 3568
B20: Google | C20: VEO3 AI | G20: https://veo3.ai/ | H20: ai@veritasconnect.com
B21: OPENAI | C21: SORA | D21: Video생성 | G21: https://sora.chatgpt.com/ | H21: ai@veritasconnect.com | J21: ChatGPT Plus ($20)
B22: VEED.IO | C22: VEED.IO | D22: Video생성 | G22: https://www.veed.io/ai-studio | H22: ai@veritasconnect.com | I22: Pro9($24)
B23: ANTHROPIC | G23: https://console.anthropic.com/cost | H23: ai@veritasconnect.com | I23: 5 | J23: 45831
A29: 결제 내역 확인(장미선 본부장 / 25.06.20)
A32: 1 | J32: 재확인필요 ( R&D)
A33: 2 | J33: AIP
A34: 3 | J34: AIP
A35: 4 | J35: 재확인필요 (Creative )
A36: 5 | J36: AIP
A37: 6 | J37: AIP
A38: 7 | J38: 재확인필요 (Creative )

Sheet NameCard
F5: @veritasconnect.com
A8: AI플랫폼개발본부(Dept. of AI Plataform Dev.) | H8: 아이디어 1(뒷면 Full, Background로) | I8: 아이디어 2(뒷면 Full, Background로)
A9: 직급 | B9: 이름 | C9: Position/Title | D9: 영문 이름 | E9: 전화번호 | F9: e-mail | H9: ASCII 아트 스타일 (이메일 앞자리) | I9: Code Style
A10: 본부장 | B10: 이상훈 | C10: Head of AI Platform Development | D10: SANG-HOON, LEE | E10: 010.8876.7086 | F10: =_xlfn.CONCAT(G10,$F$5) -> itsme@veritasconnect.com | G10: itsme | H10: ██ ████ ███ █▄▄▄█ ▄███▄ ██ ██ █ █ █ █ █ █ ██ ██ ███ █ █ ████ | I10: const chief = { name: "이상훈", role: "Chief Project Leader, AI Platform Dev.", experience: "25+ years(1999~2025)", motto: "Code is poetry, Python is My Best Friend.", status: "Always developping life" };
A12: 부장 | B12: 김창혁 | C12: Full Stack Development Manager | D12: CHANG-HYUK, KIM | E12: 010.3340.0411 | F12: =_xlfn.CONCAT(G12,$F$5) -> ch.kim@veritasconnect.com | G12: ch.kim | H12: ▄███▄ █ █ █▄▄ ██ █▄▄▄█ █ ███ █▄█ ██ █ █ █ ████ █ █ █ █ █ ██ █ █ █ | I12: function fullStackDev() { return { frontend: ["React", "PHP", "JAVA"], backend: ["Python", "dJango", "Node.js"], database: ["MySQL", "ORACLE"], superpower: "Can fix anything" }; }
A14: 과장 | B14: 김동준 | C14: Senior Backend Developer | D14: DONG-JUN, KIM | E14: 010.3171.7501 | F14: =_xlfn.CONCAT(G14,$F$5) -> junrah@veritasconnect.com | G14: junrah | H14: ██ █ █ █▄ █ ████ ▄███▄ █ █ ██ ███ █ █ █ █ █ █ █ ███ █▄██▄ █ █ █ ██ █ █ ████ █ █ | I14: class BackendMaster: def __init__(self): self.name = "김동준" self.skills = ["API", "Database", "Server", "AWS"] self.coffee_level = "Maximum" def solve_problem(self): return "Consider it done"
A16: 대리 | B16: 이진영 | C16: UI/UX Developer | D16: JIN-YEOUNG, LEE | E16: 010.9194.8162 | F16: =_xlfn.CONCAT(G16,$F$5) -> eznyeong@veritasconnect.com | G16: eznyeong | H16: ▄███▄ ████ █▄ █ █ █ ▄███▄ ▄███▄ █▄ █ ▄███▄ █ █▄▄▄ █ █ █ ███ █ █ █ █ █ █ █ █ ████ █▄▄▄ █ ██ █ █ ████ ████ █ ██ ████ | I16: .designer { creativity: 100% important; user-focus: always; pixel-perfect: true; coffee-addiction: high; }
